recursion_tree_plotter/__init__.py
recursion_tree_plotter/main.py
recursion_tree_plotter-1.0.1.dist-info/LICENSE
recursion_tree_plotter-1.0.1.dist-info/METADATA
recursion_tree_plotter-1.0.1.dist-info/WHEEL
recursion_tree_plotter-1.0.1.dist-info/top_level.txt
recursion_tree_plotter-1.0.1.dist-info/RECORD
