Metadata-Version: 2.1
Name: recursion-tree-plotter
Version: 1.0.1
Summary: A Python package to plot the graph for calls to a recursive function
Home-page: https://github.com/nikhilkumarsingh/recursion-tree-plotter
Author: Nikhil Kumar Singh
Author-email: nikhilksingh97@gmail.com
License: MIT
Platform: UNKNOWN
Classifier: License :: OSI Approved :: MIT License
Classifier: Programming Language :: Python :: 3
Classifier: Programming Language :: Python :: 3.7
Classifier: Programming Language :: Python :: 3.8
Requires-Dist: pydot3
